{
  "item": [
    {
      "id": "11edff8d-dd4e-4d3d-aca0-d5e6dcd67bf0",
      "name": "OAuth",
      "description": {
        "content": "",
        "type": "text/plain"
      },
      "item": [
        {
          "id": "8cae06ef-a229-4014-9aab-0c09a03f2a24",
          "name": "Exchange authorization code for access token, or refresh token",
          "request": {
            "name": "Exchange authorization code for access token, or refresh token",
            "description": {},
            "url": {
              "path": [
                "oauth2",
                "v2.0",
                "token"
              ],
              "host": [
                "{{baseUrl}}"
              ],
              "query": [],
              "variable": []
            },
            "header": [
              {
                "key": "Content-Type",
                "value": "application/x-www-form-urlencoded"
              },
              {
                "key": "Accept",
                "value": "application/json"
              }
            ],
            "method": "POST",
            "auth": null,
            "body": {
              "mode": "urlencoded",
              "urlencoded": [
                {
                  "disabled": false,
                  "key": "grant_type",
                  "value": "<string>",
                  "description": "(Required) "
                },
                {
                  "disabled": false,
                  "key": "client_id",
                  "value": "<string>",
                  "description": "(Required) "
                },
                {
                  "disabled": false,
                  "key": "client_secret",
                  "value": "<string>"
                },
                {
                  "disabled": false,
                  "key": "code",
                  "value": "<string>"
                },
                {
                  "disabled": false,
                  "key": "redirect_uri",
                  "value": "<string>"
                },
                {
                  "disabled": false,
                  "key": "refresh_token",
                  "value": "<string>"
                }
              ]
            }
          },
          "response": [
            {
              "id": "e1971897-6733-4c46-986e-9b53cd63ba8a",
              "name": "Token response",
              "originalRequest": {
                "url": {
                  "path": [
                    "oauth2",
                    "v2.0",
                    "token"
                  ],
                  "host": [
                    "{{baseUrl}}"
                  ],
                  "query": [],
                  "variable": []
                },
                "header": [
                  {
                    "description": {
                      "content": "Added as a part of security scheme: oauth2",
                      "type": "text/plain"
                    },
                    "key": "Authorization",
                    "value": "<token>"
                  },
                  {
                    "key": "Accept",
                    "value": "application/json"
                  }
                ],
                "method": "POST",
                "body": {
                  "mode": "urlencoded",
                  "urlencoded": [
                    {
                      "disabled": false,
                      "description": {
                        "content": "(Required) ",
                        "type": "text/plain"
                      },
                      "key": "grant_type",
                      "value": "<string>"
                    },
                    {
                      "disabled": false,
                      "description": {
                        "content": "(Required) ",
                        "type": "text/plain"
                      },
                      "key": "client_id",
                      "value": "<string>"
                    },
                    {
                      "disabled": false,
                      "key": "client_secret",
                      "value": "<string>"
                    },
                    {
                      "disabled": false,
                      "key": "code",
                      "value": "<string>"
                    },
                    {
                      "disabled": false,
                      "key": "redirect_uri",
                      "value": "<string>"
                    },
                    {
                      "disabled": false,
                      "key": "refresh_token",
                      "value": "<string>"
                    }
                  ]
                }
              },
              "status": "OK",
              "code": 200,
              "header": [
                {
                  "key": "Content-Type",
                  "value": "application/json"
                }
              ],
              "body": "{\n  \"access_token\": \"string\",\n  \"refresh_token\": \"string\",\n  \"token_type\": \"string\",\n  \"expires_in\": 2771\n}",
              "cookie": [],
              "_postman_previewlanguage": "json"
            }
          ],
          "event": [],
          "protocolProfileBehavior": {
            "disableBodyPruning": true
          }
        }
      ],
      "event": []
    },
    {
      "id": "7d9c52cf-6a3e-4694-995e-baf0f76a33eb",
      "name": "Vehicles",
      "description": {
        "content": "",
        "type": "text/plain"
      },
      "item": [
        {
          "id": "0d4ca2a3-b547-475f-a4a5-741cd1bfd4ae",
          "name": "List vehicles enrolled with the calling FordPass account",
          "request": {
            "name": "List vehicles enrolled with the calling FordPass account",
            "description": {},
            "url": {
              "path": [
                "api",
                "fordconnect",
                "vehicles",
                "v1"
              ],
              "host": [
                "{{baseUrl}}"
              ],
              "query": [],
              "variable": []
            },
            "header": [
              {
                "key": "Accept",
                "value": "application/json"
              }
            ],
            "method": "GET",
            "auth": null
          },
          "response": [
            {
              "id": "f23e9a52-fd13-4931-ab03-7d10bb305fc3",
              "name": "JSON response",
              "originalRequest": {
                "url": {
                  "path": [
                    "api",
                    "fordconnect",
                    "vehicles",
                    "v1"
                  ],
                  "host": [
                    "{{baseUrl}}"
                  ],
                  "query": [],
                  "variable": []
                },
                "header": [
                  {
                    "description": {
                      "content": "Added as a part of security scheme: oauth2",
                      "type": "text/plain"
                    },
                    "key": "Authorization",
                    "value": "<token>"
                  },
                  {
                    "key": "Accept",
                    "value": "application/json"
                  }
                ],
                "method": "GET",
                "body": {}
              },
              "status": "OK",
              "code": 200,
              "header": [
                {
                  "key": "Content-Type",
                  "value": "application/json"
                }
              ],
              "body": "{\n  \"key_0\": 8187\n}",
              "cookie": [],
              "_postman_previewlanguage": "json"
            }
          ],
          "event": [],
          "protocolProfileBehavior": {
            "disableBodyPruning": true
          }
        },
        {
          "id": "e7827a47-dd2b-4def-9d63-5997d4e8b35d",
          "name": "Get vehicle information",
          "request": {
            "name": "Get vehicle information",
            "description": {},
            "url": {
              "path": [
                "api",
                "fordconnect",
                "vehicles",
                "v1",
                ":vehicleId"
              ],
              "host": [
                "{{baseUrl}}"
              ],
              "query": [],
              "variable": [
                {
                  "disabled": false,
                  "type": "any",
                  "value": "<string>",
                  "key": "vehicleId",
                  "description": "(Required) "
                }
              ]
            },
            "header": [
              {
                "key": "Accept",
                "value": "application/json"
              }
            ],
            "method": "GET",
            "auth": null
          },
          "response": [
            {
              "id": "6d4c9d8d-7c37-43b6-a238-81b77d55f155",
              "name": "JSON response",
              "originalRequest": {
                "url": {
                  "path": [
                    "api",
                    "fordconnect",
                    "vehicles",
                    "v1",
                    ":vehicleId"
                  ],
                  "host": [
                    "{{baseUrl}}"
                  ],
                  "query": [],
                  "variable": [
                    {
                      "disabled": false,
                      "type": "any",
                      "value": "<string>",
                      "key": "vehicleId",
                      "description": "(Required) "
                    }
                  ]
                },
                "header": [
                  {
                    "description": {
                      "content": "Added as a part of security scheme: oauth2",
                      "type": "text/plain"
                    },
                    "key": "Authorization",
                    "value": "<token>"
                  },
                  {
                    "key": "Accept",
                    "value": "application/json"
                  }
                ],
                "method": "GET",
                "body": {}
              },
              "status": "OK",
              "code": 200,
              "header": [
                {
                  "key": "Content-Type",
                  "value": "application/json"
                }
              ],
              "body": "{\n  \"key_0\": 8187\n}",
              "cookie": [],
              "_postman_previewlanguage": "json"
            }
          ],
          "event": [],
          "protocolProfileBehavior": {
            "disableBodyPruning": true
          }
        }
      ],
      "event": []
    },
    {
      "id": "2e706373-f282-4639-84cc-fec0f877d937",
      "name": "Commands",
      "description": {
        "content": "",
        "type": "text/plain"
      },
      "item": [
        {
          "id": "065e9a92-c0de-4876-8975-a2054993c37e",
          "name": "Issue a lock command",
          "request": {
            "name": "Issue a lock command",
            "description": {},
            "url": {
              "path": [
                "api",
                "fordconnect",
                "vehicles",
                "v1",
                ":vehicleId",
                "lock"
              ],
              "host": [
                "{{baseUrl}}"
              ],
              "query": [],
              "variable": [
                {
                  "disabled": false,
                  "type": "any",
                  "value": "<string>",
                  "key": "vehicleId",
                  "description": "(Required) "
                }
              ]
            },
            "header": [
              {
                "key": "Accept",
                "value": "application/json"
              }
            ],
            "method": "POST",
            "auth": null
          },
          "response": [
            {
              "id": "bdd74f4d-044e-44bc-885f-86f3ad1ca6b9",
              "name": "Command accepted",
              "originalRequest": {
                "url": {
                  "path": [
                    "api",
                    "fordconnect",
                    "vehicles",
                    "v1",
                    ":vehicleId",
                    "lock"
                  ],
                  "host": [
                    "{{baseUrl}}"
                  ],
                  "query": [],
                  "variable": [
                    {
                      "disabled": false,
                      "type": "any",
                      "value": "<string>",
                      "key": "vehicleId",
                      "description": "(Required) "
                    }
                  ]
                },
                "header": [
                  {
                    "description": {
                      "content": "Added as a part of security scheme: oauth2",
                      "type": "text/plain"
                    },
                    "key": "Authorization",
                    "value": "<token>"
                  },
                  {
                    "key": "Accept",
                    "value": "application/json"
                  }
                ],
                "method": "POST",
                "body": {}
              },
              "status": "Accepted",
              "code": 202,
              "header": [
                {
                  "key": "Content-Type",
                  "value": "application/json"
                }
              ],
              "body": "{\n  \"status\": 8510,\n  \"commandStatus\": \"string\",\n  \"commandId\": \"string\"\n}",
              "cookie": [],
              "_postman_previewlanguage": "json"
            }
          ],
          "event": [],
          "protocolProfileBehavior": {
            "disableBodyPruning": true
          }
        },
        {
          "id": "16cea4ae-17b6-40dd-b410-9c8bcf938bf3",
          "name": "Check lock command status",
          "request": {
            "name": "Check lock command status",
            "description": {},
            "url": {
              "path": [
                "api",
                "fordconnect",
                "vehicles",
                "v1",
                ":vehicleId",
                "lock",
                ":commandId"
              ],
              "host": [
                "{{baseUrl}}"
              ],
              "query": [],
              "variable": [
                {
                  "disabled": false,
                  "type": "any",
                  "value": "<string>",
                  "key": "vehicleId",
                  "description": "(Required) "
                },
                {
                  "disabled": false,
                  "type": "any",
                  "value": "<string>",
                  "key": "commandId",
                  "description": "(Required) "
                }
              ]
            },
            "header": [
              {
                "key": "Accept",
                "value": "application/json"
              }
            ],
            "method": "GET",
            "auth": null
          },
          "response": [
            {
              "id": "72f85b6d-de71-492d-807b-f69cc9094faf",
              "name": "JSON response",
              "originalRequest": {
                "url": {
                  "path": [
                    "api",
                    "fordconnect",
                    "vehicles",
                    "v1",
                    ":vehicleId",
                    "lock",
                    ":commandId"
                  ],
                  "host": [
                    "{{baseUrl}}"
                  ],
                  "query": [],
                  "variable": [
                    {
                      "disabled": false,
                      "type": "any",
                      "value": "<string>",
                      "key": "vehicleId",
                      "description": "(Required) "
                    },
                    {
                      "disabled": false,
                      "type": "any",
                      "value": "<string>",
                      "key": "commandId",
                      "description": "(Required) "
                    }
                  ]
                },
                "header": [
                  {
                    "description": {
                      "content": "Added as a part of security scheme: oauth2",
                      "type": "text/plain"
                    },
                    "key": "Authorization",
                    "value": "<token>"
                  },
                  {
                    "key": "Accept",
                    "value": "application/json"
                  }
                ],
                "method": "GET",
                "body": {}
              },
              "status": "OK",
              "code": 200,
              "header": [
                {
                  "key": "Content-Type",
                  "value": "application/json"
                }
              ],
              "body": "{\n  \"key_0\": 8187\n}",
              "cookie": [],
              "_postman_previewlanguage": "json"
            }
          ],
          "event": [],
          "protocolProfileBehavior": {
            "disableBodyPruning": true
          }
        },
        {
          "id": "0b24bf44-ab89-419c-a9a7-55b3e3a022d4",
          "name": "Issue an unlock command",
          "request": {
            "name": "Issue an unlock command",
            "description": {},
            "url": {
              "path": [
                "api",
                "fordconnect",
                "vehicles",
                "v1",
                ":vehicleId",
                "unlock"
              ],
              "host": [
                "{{baseUrl}}"
              ],
              "query": [],
              "variable": [
                {
                  "disabled": false,
                  "type": "any",
                  "value": "<string>",
                  "key": "vehicleId",
                  "description": "(Required) "
                }
              ]
            },
            "header": [
              {
                "key": "Accept",
                "value": "application/json"
              }
            ],
            "method": "POST",
            "auth": null
          },
          "response": [
            {
              "id": "7a62f1ed-ed2b-4ab8-a144-90f8c17f8a35",
              "name": "Command accepted",
              "originalRequest": {
                "url": {
                  "path": [
                    "api",
                    "fordconnect",
                    "vehicles",
                    "v1",
                    ":vehicleId",
                    "unlock"
                  ],
                  "host": [
                    "{{baseUrl}}"
                  ],
                  "query": [],
                  "variable": [
                    {
                      "disabled": false,
                      "type": "any",
                      "value": "<string>",
                      "key": "vehicleId",
                      "description": "(Required) "
                    }
                  ]
                },
                "header": [
                  {
                    "description": {
                      "content": "Added as a part of security scheme: oauth2",
                      "type": "text/plain"
                    },
                    "key": "Authorization",
                    "value": "<token>"
                  },
                  {
                    "key": "Accept",
                    "value": "application/json"
                  }
                ],
                "method": "POST",
                "body": {}
              },
              "status": "Accepted",
              "code": 202,
              "header": [
                {
                  "key": "Content-Type",
                  "value": "application/json"
                }
              ],
              "body": "{\n  \"status\": 8510,\n  \"commandStatus\": \"string\",\n  \"commandId\": \"string\"\n}",
              "cookie": [],
              "_postman_previewlanguage": "json"
            }
          ],
          "event": [],
          "protocolProfileBehavior": {
            "disableBodyPruning": true
          }
        },
        {
          "id": "0955311d-99a3-4350-9320-a050d2f38275",
          "name": "Check unlock command status",
          "request": {
            "name": "Check unlock command status",
            "description": {},
            "url": {
              "path": [
                "api",
                "fordconnect",
                "vehicles",
                "v1",
                ":vehicleId",
                "unlock",
                ":commandId"
              ],
              "host": [
                "{{baseUrl}}"
              ],
              "query": [],
              "variable": [
                {
                  "disabled": false,
                  "type": "any",
                  "value": "<string>",
                  "key": "vehicleId",
                  "description": "(Required) "
                },
                {
                  "disabled": false,
                  "type": "any",
                  "value": "<string>",
                  "key": "commandId",
                  "description": "(Required) "
                }
              ]
            },
            "header": [
              {
                "key": "Accept",
                "value": "application/json"
              }
            ],
            "method": "GET",
            "auth": null
          },
          "response": [
            {
              "id": "63544c16-356e-4bfb-8dbd-0e683005c5f6",
              "name": "JSON response",
              "originalRequest": {
                "url": {
                  "path": [
                    "api",
                    "fordconnect",
                    "vehicles",
                    "v1",
                    ":vehicleId",
                    "unlock",
                    ":commandId"
                  ],
                  "host": [
                    "{{baseUrl}}"
                  ],
                  "query": [],
                  "variable": [
                    {
                      "disabled": false,
                      "type": "any",
                      "value": "<string>",
                      "key": "vehicleId",
                      "description": "(Required) "
                    },
                    {
                      "disabled": false,
                      "type": "any",
                      "value": "<string>",
                      "key": "commandId",
                      "description": "(Required) "
                    }
                  ]
                },
                "header": [
                  {
                    "description": {
                      "content": "Added as a part of security scheme: oauth2",
                      "type": "text/plain"
                    },
                    "key": "Authorization",
                    "value": "<token>"
                  },
                  {
                    "key": "Accept",
                    "value": "application/json"
                  }
                ],
                "method": "GET",
                "body": {}
              },
              "status": "OK",
              "code": 200,
              "header": [
                {
                  "key": "Content-Type",
                  "value": "application/json"
                }
              ],
              "body": "{\n  \"key_0\": 8187\n}",
              "cookie": [],
              "_postman_previewlanguage": "json"
            }
          ],
          "event": [],
          "protocolProfileBehavior": {
            "disableBodyPruning": true
          }
        },
        {
          "id": "701b3a8e-6dfc-4648-9610-bb76c6833b2a",
          "name": "Remote start engine",
          "request": {
            "name": "Remote start engine",
            "description": {},
            "url": {
              "path": [
                "api",
                "fordconnect",
                "vehicles",
                "v1",
                ":vehicleId",
                "startEngine"
              ],
              "host": [
                "{{baseUrl}}"
              ],
              "query": [],
              "variable": [
                {
                  "disabled": false,
                  "type": "any",
                  "value": "<string>",
                  "key": "vehicleId",
                  "description": "(Required) "
                }
              ]
            },
            "header": [
              {
                "key": "Accept",
                "value": "application/json"
              }
            ],
            "method": "POST",
            "auth": null
          },
          "response": [
            {
              "id": "bad9f8f8-96a9-4682-b9a7-979d9dbb2f70",
              "name": "Command accepted",
              "originalRequest": {
                "url": {
                  "path": [
                    "api",
                    "fordconnect",
                    "vehicles",
                    "v1",
                    ":vehicleId",
                    "startEngine"
                  ],
                  "host": [
                    "{{baseUrl}}"
                  ],
                  "query": [],
                  "variable": [
                    {
                      "disabled": false,
                      "type": "any",
                      "value": "<string>",
                      "key": "vehicleId",
                      "description": "(Required) "
                    }
                  ]
                },
                "header": [
                  {
                    "description": {
                      "content": "Added as a part of security scheme: oauth2",
                      "type": "text/plain"
                    },
                    "key": "Authorization",
                    "value": "<token>"
                  },
                  {
                    "key": "Accept",
                    "value": "application/json"
                  }
                ],
                "method": "POST",
                "body": {}
              },
              "status": "Accepted",
              "code": 202,
              "header": [
                {
                  "key": "Content-Type",
                  "value": "application/json"
                }
              ],
              "body": "{\n  \"status\": 8510,\n  \"commandStatus\": \"string\",\n  \"commandId\": \"string\"\n}",
              "cookie": [],
              "_postman_previewlanguage": "json"
            }
          ],
          "event": [],
          "protocolProfileBehavior": {
            "disableBodyPruning": true
          }
        },
        {
          "id": "75f2e6e1-fabb-4255-a36e-1177483281e0",
          "name": "Remote stop engine",
          "request": {
            "name": "Remote stop engine",
            "description": {},
            "url": {
              "path": [
                "api",
                "fordconnect",
                "vehicles",
                "v1",
                ":vehicleId",
                "stopEngine"
              ],
              "host": [
                "{{baseUrl}}"
              ],
              "query": [],
              "variable": [
                {
                  "disabled": false,
                  "type": "any",
                  "value": "<string>",
                  "key": "vehicleId",
                  "description": "(Required) "
                }
              ]
            },
            "header": [
              {
                "key": "Accept",
                "value": "application/json"
              }
            ],
            "method": "POST",
            "auth": null
          },
          "response": [
            {
              "id": "ce8d875c-b3f3-4115-9b2e-4de04b3f5d54",
              "name": "Command accepted",
              "originalRequest": {
                "url": {
                  "path": [
                    "api",
                    "fordconnect",
                    "vehicles",
                    "v1",
                    ":vehicleId",
                    "stopEngine"
                  ],
                  "host": [
                    "{{baseUrl}}"
                  ],
                  "query": [],
                  "variable": [
                    {
                      "disabled": false,
                      "type": "any",
                      "value": "<string>",
                      "key": "vehicleId",
                      "description": "(Required) "
                    }
                  ]
                },
                "header": [
                  {
                    "description": {
                      "content": "Added as a part of security scheme: oauth2",
                      "type": "text/plain"
                    },
                    "key": "Authorization",
                    "value": "<token>"
                  },
                  {
                    "key": "Accept",
                    "value": "application/json"
                  }
                ],
                "method": "POST",
                "body": {}
              },
              "status": "Accepted",
              "code": 202,
              "header": [
                {
                  "key": "Content-Type",
                  "value": "application/json"
                }
              ],
              "body": "{\n  \"status\": 8510,\n  \"commandStatus\": \"string\",\n  \"commandId\": \"string\"\n}",
              "cookie": [],
              "_postman_previewlanguage": "json"
            }
          ],
          "event": [],
          "protocolProfileBehavior": {
            "disableBodyPruning": true
          }
        },
        {
          "id": "48f307c5-0b11-4990-84d9-ef98861f2b60",
          "name": "Wake the vehicle from sleep",
          "request": {
            "name": "Wake the vehicle from sleep",
            "description": {},
            "url": {
              "path": [
                "api",
                "fordconnect",
                "vehicles",
                "v1",
                ":vehicleId",
                "wake"
              ],
              "host": [
                "{{baseUrl}}"
              ],
              "query": [],
              "variable": [
                {
                  "disabled": false,
                  "type": "any",
                  "value": "<string>",
                  "key": "vehicleId",
                  "description": "(Required) "
                }
              ]
            },
            "header": [
              {
                "key": "Accept",
                "value": "application/json"
              }
            ],
            "method": "POST",
            "auth": null
          },
          "response": [
            {
              "id": "50bccd23-4188-456b-8a82-ac478edce950",
              "name": "Command accepted",
              "originalRequest": {
                "url": {
                  "path": [
                    "api",
                    "fordconnect",
                    "vehicles",
                    "v1",
                    ":vehicleId",
                    "wake"
                  ],
                  "host": [
                    "{{baseUrl}}"
                  ],
                  "query": [],
                  "variable": [
                    {
                      "disabled": false,
                      "type": "any",
                      "value": "<string>",
                      "key": "vehicleId",
                      "description": "(Required) "
                    }
                  ]
                },
                "header": [
                  {
                    "description": {
                      "content": "Added as a part of security scheme: oauth2",
                      "type": "text/plain"
                    },
                    "key": "Authorization",
                    "value": "<token>"
                  },
                  {
                    "key": "Accept",
                    "value": "application/json"
                  }
                ],
                "method": "POST",
                "body": {}
              },
              "status": "Accepted",
              "code": 202,
              "header": [
                {
                  "key": "Content-Type",
                  "value": "application/json"
                }
              ],
              "body": "{\n  \"status\": 8510,\n  \"commandStatus\": \"string\",\n  \"commandId\": \"string\"\n}",
              "cookie": [],
              "_postman_previewlanguage": "json"
            }
          ],
          "event": [],
          "protocolProfileBehavior": {
            "disableBodyPruning": true
          }
        }
      ],
      "event": []
    },
    {
      "id": "9abe0e25-d4c7-4393-b41d-a5607f1208b2",
      "name": "Charging",
      "description": {
        "content": "",
        "type": "text/plain"
      },
      "item": [
        {
          "id": "ebc5f7ee-3653-405a-b38c-9a0c89895576",
          "name": "Start charging an EV",
          "request": {
            "name": "Start charging an EV",
            "description": {},
            "url": {
              "path": [
                "api",
                "fordconnect",
                "vehicles",
                "v1",
                ":vehicleId",
                "startCharge"
              ],
              "host": [
                "{{baseUrl}}"
              ],
              "query": [],
              "variable": [
                {
                  "disabled": false,
                  "type": "any",
                  "value": "<string>",
                  "key": "vehicleId",
                  "description": "(Required) "
                }
              ]
            },
            "header": [
              {
                "key": "Accept",
                "value": "application/json"
              }
            ],
            "method": "POST",
            "auth": null
          },
          "response": [
            {
              "id": "86cb67e1-df00-4d4f-bbba-5d0c61962fd4",
              "name": "Command accepted",
              "originalRequest": {
                "url": {
                  "path": [
                    "api",
                    "fordconnect",
                    "vehicles",
                    "v1",
                    ":vehicleId",
                    "startCharge"
                  ],
                  "host": [
                    "{{baseUrl}}"
                  ],
                  "query": [],
                  "variable": [
                    {
                      "disabled": false,
                      "type": "any",
                      "value": "<string>",
                      "key": "vehicleId",
                      "description": "(Required) "
                    }
                  ]
                },
                "header": [
                  {
                    "description": {
                      "content": "Added as a part of security scheme: oauth2",
                      "type": "text/plain"
                    },
                    "key": "Authorization",
                    "value": "<token>"
                  },
                  {
                    "key": "Accept",
                    "value": "application/json"
                  }
                ],
                "method": "POST",
                "body": {}
              },
              "status": "Accepted",
              "code": 202,
              "header": [
                {
                  "key": "Content-Type",
                  "value": "application/json"
                }
              ],
              "body": "{\n  \"status\": 8510,\n  \"commandStatus\": \"string\",\n  \"commandId\": \"string\"\n}",
              "cookie": [],
              "_postman_previewlanguage": "json"
            }
          ],
          "event": [],
          "protocolProfileBehavior": {
            "disableBodyPruning": true
          }
        },
        {
          "id": "1897de88-d8e8-4a1e-97a1-720d7c7ba178",
          "name": "Stop charging an EV",
          "request": {
            "name": "Stop charging an EV",
            "description": {},
            "url": {
              "path": [
                "api",
                "fordconnect",
                "vehicles",
                "v1",
                ":vehicleId",
                "stopCharge"
              ],
              "host": [
                "{{baseUrl}}"
              ],
              "query": [],
              "variable": [
                {
                  "disabled": false,
                  "type": "any",
                  "value": "<string>",
                  "key": "vehicleId",
                  "description": "(Required) "
                }
              ]
            },
            "header": [
              {
                "key": "Accept",
                "value": "application/json"
              }
            ],
            "method": "POST",
            "auth": null
          },
          "response": [
            {
              "id": "34b33937-f93d-45f7-a191-7839843e028c",
              "name": "Command accepted",
              "originalRequest": {
                "url": {
                  "path": [
                    "api",
                    "fordconnect",
                    "vehicles",
                    "v1",
                    ":vehicleId",
                    "stopCharge"
                  ],
                  "host": [
                    "{{baseUrl}}"
                  ],
                  "query": [],
                  "variable": [
                    {
                      "disabled": false,
                      "type": "any",
                      "value": "<string>",
                      "key": "vehicleId",
                      "description": "(Required) "
                    }
                  ]
                },
                "header": [
                  {
                    "description": {
                      "content": "Added as a part of security scheme: oauth2",
                      "type": "text/plain"
                    },
                    "key": "Authorization",
                    "value": "<token>"
                  },
                  {
                    "key": "Accept",
                    "value": "application/json"
                  }
                ],
                "method": "POST",
                "body": {}
              },
              "status": "Accepted",
              "code": 202,
              "header": [
                {
                  "key": "Content-Type",
                  "value": "application/json"
                }
              ],
              "body": "{\n  \"status\": 8510,\n  \"commandStatus\": \"string\",\n  \"commandId\": \"string\"\n}",
              "cookie": [],
              "_postman_previewlanguage": "json"
            }
          ],
          "event": [],
          "protocolProfileBehavior": {
            "disableBodyPruning": true
          }
        },
        {
          "id": "d505a83f-35f1-4c9e-8e3a-38933bf32fe7",
          "name": "Get EV charge schedule",
          "request": {
            "name": "Get EV charge schedule",
            "description": {},
            "url": {
              "path": [
                "api",
                "fordconnect",
                "vehicles",
                "v1",
                ":vehicleId",
                "chargeSchedules"
              ],
              "host": [
                "{{baseUrl}}"
              ],
              "query": [],
              "variable": [
                {
                  "disabled": false,
                  "type": "any",
                  "value": "<string>",
                  "key": "vehicleId",
                  "description": "(Required) "
                }
              ]
            },
            "header": [
              {
                "key": "Accept",
                "value": "application/json"
              }
            ],
            "method": "GET",
            "auth": null
          },
          "response": [
            {
              "id": "ef780f16-53b8-474b-a84d-3e7827f968aa",
              "name": "JSON response",
              "originalRequest": {
                "url": {
                  "path": [
                    "api",
                    "fordconnect",
                    "vehicles",
                    "v1",
                    ":vehicleId",
                    "chargeSchedules"
                  ],
                  "host": [
                    "{{baseUrl}}"
                  ],
                  "query": [],
                  "variable": [
                    {
                      "disabled": false,
                      "type": "any",
                      "value": "<string>",
                      "key": "vehicleId",
                      "description": "(Required) "
                    }
                  ]
                },
                "header": [
                  {
                    "description": {
                      "content": "Added as a part of security scheme: oauth2",
                      "type": "text/plain"
                    },
                    "key": "Authorization",
                    "value": "<token>"
                  },
                  {
                    "key": "Accept",
                    "value": "application/json"
                  }
                ],
                "method": "GET",
                "body": {}
              },
              "status": "OK",
              "code": 200,
              "header": [
                {
                  "key": "Content-Type",
                  "value": "application/json"
                }
              ],
              "body": "{\n  \"key_0\": 8187\n}",
              "cookie": [],
              "_postman_previewlanguage": "json"
            }
          ],
          "event": [],
          "protocolProfileBehavior": {
            "disableBodyPruning": true
          }
        },
        {
          "id": "d6aa95dc-60ee-47ed-bcb9-257011057745",
          "name": "Get configured departure times",
          "request": {
            "name": "Get configured departure times",
            "description": {},
            "url": {
              "path": [
                "api",
                "fordconnect",
                "vehicles",
                "v1",
                ":vehicleId",
                "departureTimes"
              ],
              "host": [
                "{{baseUrl}}"
              ],
              "query": [],
              "variable": [
                {
                  "disabled": false,
                  "type": "any",
                  "value": "<string>",
                  "key": "vehicleId",
                  "description": "(Required) "
                }
              ]
            },
            "header": [
              {
                "key": "Accept",
                "value": "application/json"
              }
            ],
            "method": "GET",
            "auth": null
          },
          "response": [
            {
              "id": "6b1bca8d-4b8e-4ab1-9873-9891ec2f7e13",
              "name": "JSON response",
              "originalRequest": {
                "url": {
                  "path": [
                    "api",
                    "fordconnect",
                    "vehicles",
                    "v1",
                    ":vehicleId",
                    "departureTimes"
                  ],
                  "host": [
                    "{{baseUrl}}"
                  ],
                  "query": [],
                  "variable": [
                    {
                      "disabled": false,
                      "type": "any",
                      "value": "<string>",
                      "key": "vehicleId",
                      "description": "(Required) "
                    }
                  ]
                },
                "header": [
                  {
                    "description": {
                      "content": "Added as a part of security scheme: oauth2",
                      "type": "text/plain"
                    },
                    "key": "Authorization",
                    "value": "<token>"
                  },
                  {
                    "key": "Accept",
                    "value": "application/json"
                  }
                ],
                "method": "GET",
                "body": {}
              },
              "status": "OK",
              "code": 200,
              "header": [
                {
                  "key": "Content-Type",
                  "value": "application/json"
                }
              ],
              "body": "{\n  \"key_0\": 8187\n}",
              "cookie": [],
              "_postman_previewlanguage": "json"
            }
          ],
          "event": [],
          "protocolProfileBehavior": {
            "disableBodyPruning": true
          }
        }
      ],
      "event": []
    },
    {
      "id": "bd0f1df0-e7ce-4111-9f80-1cae150a6aa1",
      "name": "Status",
      "description": {
        "content": "",
        "type": "text/plain"
      },
      "item": [
        {
          "id": "d613d996-a72f-46aa-8b86-c34b1a5b28d0",
          "name": "Request a fresh vehicle status snapshot",
          "request": {
            "name": "Request a fresh vehicle status snapshot",
            "description": {},
            "url": {
              "path": [
                "api",
                "fordconnect",
                "vehicles",
                "v1",
                ":vehicleId",
                "status"
              ],
              "host": [
                "{{baseUrl}}"
              ],
              "query": [],
              "variable": [
                {
                  "disabled": false,
                  "type": "any",
                  "value": "<string>",
                  "key": "vehicleId",
                  "description": "(Required) "
                }
              ]
            },
            "header": [
              {
                "key": "Accept",
                "value": "application/json"
              }
            ],
            "method": "POST",
            "auth": null
          },
          "response": [
            {
              "id": "e0b65611-8602-4d1f-b9cc-72604e88bb65",
              "name": "Command accepted",
              "originalRequest": {
                "url": {
                  "path": [
                    "api",
                    "fordconnect",
                    "vehicles",
                    "v1",
                    ":vehicleId",
                    "status"
                  ],
                  "host": [
                    "{{baseUrl}}"
                  ],
                  "query": [],
                  "variable": [
                    {
                      "disabled": false,
                      "type": "any",
                      "value": "<string>",
                      "key": "vehicleId",
                      "description": "(Required) "
                    }
                  ]
                },
                "header": [
                  {
                    "description": {
                      "content": "Added as a part of security scheme: oauth2",
                      "type": "text/plain"
                    },
                    "key": "Authorization",
                    "value": "<token>"
                  },
                  {
                    "key": "Accept",
                    "value": "application/json"
                  }
                ],
                "method": "POST",
                "body": {}
              },
              "status": "Accepted",
              "code": 202,
              "header": [
                {
                  "key": "Content-Type",
                  "value": "application/json"
                }
              ],
              "body": "{\n  \"status\": 8510,\n  \"commandStatus\": \"string\",\n  \"commandId\": \"string\"\n}",
              "cookie": [],
              "_postman_previewlanguage": "json"
            }
          ],
          "event": [],
          "protocolProfileBehavior": {
            "disableBodyPruning": true
          }
        },
        {
          "id": "c3ef05c6-d1ff-4e79-b5f7-81499c2be526",
          "name": "Request vehicle location",
          "request": {
            "name": "Request vehicle location",
            "description": {},
            "url": {
              "path": [
                "api",
                "fordconnect",
                "vehicles",
                "v1",
                ":vehicleId",
                "location"
              ],
              "host": [
                "{{baseUrl}}"
              ],
              "query": [],
              "variable": [
                {
                  "disabled": false,
                  "type": "any",
                  "value": "<string>",
                  "key": "vehicleId",
                  "description": "(Required) "
                }
              ]
            },
            "header": [
              {
                "key": "Accept",
                "value": "application/json"
              }
            ],
            "method": "POST",
            "auth": null
          },
          "response": [
            {
              "id": "48b9ac7d-f317-48ac-94c8-d96b5ea0cf6d",
              "name": "JSON response",
              "originalRequest": {
                "url": {
                  "path": [
                    "api",
                    "fordconnect",
                    "vehicles",
                    "v1",
                    ":vehicleId",
                    "location"
                  ],
                  "host": [
                    "{{baseUrl}}"
                  ],
                  "query": [],
                  "variable": [
                    {
                      "disabled": false,
                      "type": "any",
                      "value": "<string>",
                      "key": "vehicleId",
                      "description": "(Required) "
                    }
                  ]
                },
                "header": [
                  {
                    "description": {
                      "content": "Added as a part of security scheme: oauth2",
                      "type": "text/plain"
                    },
                    "key": "Authorization",
                    "value": "<token>"
                  },
                  {
                    "key": "Accept",
                    "value": "application/json"
                  }
                ],
                "method": "POST",
                "body": {}
              },
              "status": "OK",
              "code": 200,
              "header": [
                {
                  "key": "Content-Type",
                  "value": "application/json"
                }
              ],
              "body": "{\n  \"key_0\": 8187\n}",
              "cookie": [],
              "_postman_previewlanguage": "json"
            }
          ],
          "event": [],
          "protocolProfileBehavior": {
            "disableBodyPruning": true
          }
        }
      ],
      "event": []
    },
    {
      "id": "cad5d3ec-52f9-4155-9e33-991a49a35935",
      "name": "Images",
      "description": {
        "content": "",
        "type": "text/plain"
      },
      "item": [
        {
          "id": "67424518-f47a-44b8-a360-9fd7d683c4fa",
          "name": "Get vehicle thumbnail image",
          "request": {
            "name": "Get vehicle thumbnail image",
            "description": {},
            "url": {
              "path": [
                "api",
                "fordconnect",
                "vehicles",
                "v1",
                ":vehicleId",
                "images",
                "thumbnail"
              ],
              "host": [
                "{{baseUrl}}"
              ],
              "query": [],
              "variable": [
                {
                  "disabled": false,
                  "type": "any",
                  "value": "<string>",
                  "key": "vehicleId",
                  "description": "(Required) "
                }
              ]
            },
            "header": [
              {
                "key": "Accept",
                "value": "image/png"
              }
            ],
            "method": "GET",
            "auth": null
          },
          "response": [
            {
              "id": "1fcb9452-d927-4876-a42e-ddefb8cb8ee6",
              "name": "Image",
              "originalRequest": {
                "url": {
                  "path": [
                    "api",
                    "fordconnect",
                    "vehicles",
                    "v1",
                    ":vehicleId",
                    "images",
                    "thumbnail"
                  ],
                  "host": [
                    "{{baseUrl}}"
                  ],
                  "query": [],
                  "variable": [
                    {
                      "disabled": false,
                      "type": "any",
                      "value": "<string>",
                      "key": "vehicleId",
                      "description": "(Required) "
                    }
                  ]
                },
                "header": [
                  {
                    "description": {
                      "content": "Added as a part of security scheme: oauth2",
                      "type": "text/plain"
                    },
                    "key": "Authorization",
                    "value": "<token>"
                  },
                  {
                    "key": "Accept",
                    "value": "image/png"
                  }
                ],
                "method": "GET",
                "body": {}
              },
              "status": "OK",
              "code": 200,
              "header": [
                {
                  "key": "Content-Type",
                  "value": "image/png"
                }
              ],
              "body": "string",
              "cookie": [],
              "_postman_previewlanguage": "text"
            }
          ],
          "event": [],
          "protocolProfileBehavior": {
            "disableBodyPruning": true
          }
        },
        {
          "id": "2a7358d4-de6a-4b7c-a86c-161a361f9f48",
          "name": "Get full vehicle image",
          "request": {
            "name": "Get full vehicle image",
            "description": {},
            "url": {
              "path": [
                "api",
                "fordconnect",
                "vehicles",
                "v1",
                ":vehicleId",
                "images",
                "full"
              ],
              "host": [
                "{{baseUrl}}"
              ],
              "query": [],
              "variable": [
                {
                  "disabled": false,
                  "type": "any",
                  "value": "<string>",
                  "key": "vehicleId",
                  "description": "(Required) "
                }
              ]
            },
            "header": [
              {
                "key": "Accept",
                "value": "image/png"
              }
            ],
            "method": "GET",
            "auth": null
          },
          "response": [
            {
              "id": "3a24a07d-8235-41f6-bb62-403d06e361bf",
              "name": "Image",
              "originalRequest": {
                "url": {
                  "path": [
                    "api",
                    "fordconnect",
                    "vehicles",
                    "v1",
                    ":vehicleId",
                    "images",
                    "full"
                  ],
                  "host": [
                    "{{baseUrl}}"
                  ],
                  "query": [],
                  "variable": [
                    {
                      "disabled": false,
                      "type": "any",
                      "value": "<string>",
                      "key": "vehicleId",
                      "description": "(Required) "
                    }
                  ]
                },
                "header": [
                  {
                    "description": {
                      "content": "Added as a part of security scheme: oauth2",
                      "type": "text/plain"
                    },
                    "key": "Authorization",
                    "value": "<token>"
                  },
                  {
                    "key": "Accept",
                    "value": "image/png"
                  }
                ],
                "method": "GET",
                "body": {}
              },
              "status": "OK",
              "code": 200,
              "header": [
                {
                  "key": "Content-Type",
                  "value": "image/png"
                }
              ],
              "body": "string",
              "cookie": [],
              "_postman_previewlanguage": "text"
            }
          ],
          "event": [],
          "protocolProfileBehavior": {
            "disableBodyPruning": true
          }
        }
      ],
      "event": []
    }
  ],
  "event": [],
  "variable": [
    {
      "type": "string",
      "value": "https://api.mps.ford.com",
      "key": "baseUrl"
    }
  ],
  "auth": {
    "type": "oauth2",
    "oauth2": [
      {
        "key": "scope",
        "value": "access"
      },
      {
        "key": "accessTokenUrl",
        "value": "https://dah2vb2cprod.b2clogin.com/914d88b1-3523-4bf6-9be4-1b96b4f6f919/oauth2/v2.0/token"
      },
      {
        "key": "authUrl",
        "value": "https://fordconnect.cv.ford.com/common/login"
      },
      {
        "key": "grant_type",
        "value": "authorization_code"
      }
    ]
  },
  "info": {
    "_postman_id": "1e7cf3f4-b872-4fd9-b06c-54ff78b68e79",
    "name": "FordConnect API",
    "schema": "https://schema.getpostman.com/json/collection/v2.1.0/collection.json",
    "description": {
      "content": "Best-effort OpenAPI 3.1 description of the FordConnect API, derived from\nthe public developer page at https://developer.ford.com/apis/fordconnect\nand the public FordConnect simulator at\nhttps://github.com/jamisonderek/ford-connect-sim. The FordConnect API\nallows authorized partners to send vehicle commands (lock, unlock, start,\nstop, charge) and retrieve vehicle status and information for enrolled\nFord and Lincoln vehicles. Authentication uses OAuth 2.0 with an\nauthorization-code grant; access tokens are passed as `Authorization:\nBearer` headers.\n\n\nContact Support:\n Name: Ford Developer",
      "type": "text/plain"
    }
  }
}